topsis_Aryan_102217019/__init__.py
topsis_Aryan_102217019/topsis_7019.py
topsis_AryanSharma_7019-0.0.1.dist-info/LICENSE.txt
topsis_AryanSharma_7019-0.0.1.dist-info/METADATA
topsis_AryanSharma_7019-0.0.1.dist-info/WHEEL
topsis_AryanSharma_7019-0.0.1.dist-info/top_level.txt
topsis_AryanSharma_7019-0.0.1.dist-info/RECORD
